odoo/addons/coupon_chatter/README.rst
odoo/addons/coupon_chatter/__init__.py
odoo/addons/coupon_chatter/__manifest__.py
odoo/addons/coupon_chatter/i18n/ca.po
odoo/addons/coupon_chatter/i18n/coupon_chatter.pot
odoo/addons/coupon_chatter/i18n/es.po
odoo/addons/coupon_chatter/i18n/it.po
odoo/addons/coupon_chatter/models/__init__.py
odoo/addons/coupon_chatter/models/loyalty_program.py
odoo/addons/coupon_chatter/readme/CONTRIBUTORS.md
odoo/addons/coupon_chatter/readme/DESCRIPTION.md
odoo/addons/coupon_chatter/readme/USAGE.md
odoo/addons/coupon_chatter/static/description/icon.png
odoo/addons/coupon_chatter/static/description/index.html
odoo/addons/coupon_chatter/views/loyalty_program_view.xml
odoo_addon_coupon_chatter-17.0.1.0.0.5.dist-info/METADATA
odoo_addon_coupon_chatter-17.0.1.0.0.5.dist-info/WHEEL
odoo_addon_coupon_chatter-17.0.1.0.0.5.dist-info/top_level.txt
odoo_addon_coupon_chatter-17.0.1.0.0.5.dist-info/RECORD
